{
    "RunKey(config_id=1, instance_id=None, seed=0, budget=0.0)": {
        "cost": -3822.9843835663764,
        "time": 0.014679431915283203,
        "status": "SUCCESS",
        "additional_info": {}
    },
    "RunKey(config_id=2, instance_id=None, seed=0, budget=0.0)": {
        "cost": -3764.4549038949212,
        "time": 0.06969499588012695,
        "status": "SUCCESS",
        "additional_info": {}
    },
    "RunKey(config_id=3, instance_id=None, seed=0, budget=0.0)": {
        "cost": -3773.801769851283,
        "time": 0.012773752212524414,
        "status": "SUCCESS",
        "additional_info": {}
    },
    "RunKey(config_id=4, instance_id=None, seed=0, budget=0.0)": {
        "cost": -3829.46150414101,
        "time": 0.012739896774291992,
        "status": "SUCCESS",
        "additional_info": {}
    },
    "RunKey(config_id=5, instance_id=None, seed=0, budget=0.0)": {
        "cost": -3631.118197771951,
        "time": 0.013135433197021484,
        "status": "SUCCESS",
        "additional_info": {}
    },
    "RunKey(config_id=6, instance_id=None, seed=0, budget=0.0)": {
        "cost": -3779.886530250166,
        "time": 0.014066457748413086,
        "status": "SUCCESS",
        "additional_info": {}
    },
    "RunKey(config_id=7, instance_id=None, seed=0, budget=0.0)": {
        "cost": -3794.9357185377876,
        "time": 0.013281822204589844,
        "status": "SUCCESS",
        "additional_info": {}
    },
    "RunKey(config_id=8, instance_id=None, seed=0, budget=0.0)": {
        "cost": -3824.189836634574,
        "time": 0.013012170791625977,
        "status": "SUCCESS",
        "additional_info": {}
    },
    "RunKey(config_id=9, instance_id=None, seed=0, budget=0.0)": {
        "cost": -3821.4179340078695,
        "time": 0.012884378433227539,
        "status": "SUCCESS",
        "additional_info": {}
    },
    "RunKey(config_id=10, instance_id=None, seed=0, budget=0.0)": {
        "cost": -3788.6336467537694,
        "time": 0.012674331665039062,
        "status": "SUCCESS",
        "additional_info": {}
    },
    "RunKey(config_id=11, instance_id=None, seed=0, budget=0.0)": {
        "cost": -3814.2970729838653,
        "time": 0.012726068496704102,
        "status": "SUCCESS",
        "additional_info": {}
    },
    "RunKey(config_id=12, instance_id=None, seed=0, budget=0.0)": {
        "cost": -3818.5931214946327,
        "time": 0.01266932487487793,
        "status": "SUCCESS",
        "additional_info": {}
    },
    "RunKey(config_id=13, instance_id=None, seed=0, budget=0.0)": {
        "cost": -3690.995466141529,
        "time": 0.013138294219970703,
        "status": "SUCCESS",
        "additional_info": {}
    },
    "RunKey(config_id=14, instance_id=None, seed=0, budget=0.0)": {
        "cost": -3879.2642223617067,
        "time": 0.013557195663452148,
        "status": "SUCCESS",
        "additional_info": {}
    },
    "RunKey(config_id=15, instance_id=None, seed=0, budget=0.0)": {
        "cost": -3763.004309961619,
        "time": 0.012946605682373047,
        "status": "SUCCESS",
        "additional_info": {}
    },
    "RunKey(config_id=16, instance_id=None, seed=0, budget=0.0)": {
        "cost": -3748.1175288962418,
        "time": 0.012651920318603516,
        "status": "SUCCESS",
        "additional_info": {}
    },
    "RunKey(config_id=17, instance_id=None, seed=0, budget=0.0)": {
        "cost": -3788.8658195978483,
        "time": 0.01266336441040039,
        "status": "SUCCESS",
        "additional_info": {}
    },
    "RunKey(config_id=18, instance_id=None, seed=0, budget=0.0)": {
        "cost": -3803.6228803737104,
        "time": 0.012752294540405273,
        "status": "SUCCESS",
        "additional_info": {}
    },
    "RunKey(config_id=19, instance_id=None, seed=0, budget=0.0)": {
        "cost": -3765.850780081397,
        "time": 0.01275491714477539,
        "status": "SUCCESS",
        "additional_info": {}
    },
    "RunKey(config_id=20, instance_id=None, seed=0, budget=0.0)": {
        "cost": -3773.7853111083696,
        "time": 0.012673377990722656,
        "status": "SUCCESS",
        "additional_info": {}
    },
    "RunKey(config_id=21, instance_id=None, seed=0, budget=0.0)": {
        "cost": -3814.1121377288414,
        "time": 0.012779712677001953,
        "status": "SUCCESS",
        "additional_info": {}
    },
    "RunKey(config_id=22, instance_id=None, seed=0, budget=0.0)": {
        "cost": -3837.8444783096984,
        "time": 0.012694597244262695,
        "status": "SUCCESS",
        "additional_info": {}
    },
    "RunKey(config_id=23, instance_id=None, seed=0, budget=0.0)": {
        "cost": -3596.736780845477,
        "time": 0.01274251937866211,
        "status": "SUCCESS",
        "additional_info": {}
    },
    "RunKey(config_id=24, instance_id=None, seed=0, budget=0.0)": {
        "cost": -3829.181282552456,
        "time": 0.012684106826782227,
        "status": "SUCCESS",
        "additional_info": {}
    },
    "RunKey(config_id=25, instance_id=None, seed=0, budget=0.0)": {
        "cost": -3793.786226130085,
        "time": 0.012723684310913086,
        "status": "SUCCESS",
        "additional_info": {}
    },
    "RunKey(config_id=26, instance_id=None, seed=0, budget=0.0)": {
        "cost": -3792.9036238532294,
        "time": 0.012607812881469727,
        "status": "SUCCESS",
        "additional_info": {}
    },
    "RunKey(config_id=27, instance_id=None, seed=0, budget=0.0)": {
        "cost": -3878.339949557697,
        "time": 0.015425443649291992,
        "status": "SUCCESS",
        "additional_info": {}
    },
    "RunKey(config_id=28, instance_id=None, seed=0, budget=0.0)": {
        "cost": -3852.7617169253112,
        "time": 0.014250040054321289,
        "status": "SUCCESS",
        "additional_info": {}
    },
    "RunKey(config_id=29, instance_id=None, seed=0, budget=0.0)": {
        "cost": -3841.8036531216335,
        "time": 0.014153003692626953,
        "status": "SUCCESS",
        "additional_info": {}
    },
    "RunKey(config_id=30, instance_id=None, seed=0, budget=0.0)": {
        "cost": -3829.193151424263,
        "time": 0.014159679412841797,
        "status": "SUCCESS",
        "additional_info": {}
    },
    "RunKey(config_id=31, instance_id=None, seed=0, budget=0.0)": {
        "cost": -3882.747121189897,
        "time": 0.015427589416503906,
        "status": "SUCCESS",
        "additional_info": {}
    },
    "RunKey(config_id=32, instance_id=None, seed=0, budget=0.0)": {
        "cost": -3880.182444034638,
        "time": 0.013485193252563477,
        "status": "SUCCESS",
        "additional_info": {}
    },
    "RunKey(config_id=33, instance_id=None, seed=0, budget=0.0)": {
        "cost": -3877.648664634455,
        "time": 0.013559103012084961,
        "status": "SUCCESS",
        "additional_info": {}
    },
    "RunKey(config_id=34, instance_id=None, seed=0, budget=0.0)": {
        "cost": -3807.033208185223,
        "time": 0.013406991958618164,
        "status": "SUCCESS",
        "additional_info": {}
    },
    "RunKey(config_id=35, instance_id=None, seed=0, budget=0.0)": {
        "cost": -3868.72233714336,
        "time": 0.024580717086791992,
        "status": "SUCCESS",
        "additional_info": {}
    },
    "RunKey(config_id=36, instance_id=None, seed=0, budget=0.0)": {
        "cost": -3882.0148345827415,
        "time": 0.014183521270751953,
        "status": "SUCCESS",
        "additional_info": {}
    },
    "RunKey(config_id=37, instance_id=None, seed=0, budget=0.0)": {
        "cost": -3754.990346534595,
        "time": 0.013283967971801758,
        "status": "SUCCESS",
        "additional_info": {}
    },
    "RunKey(config_id=38, instance_id=None, seed=0, budget=0.0)": {
        "cost": -3810.252112839478,
        "time": 0.01301884651184082,
        "status": "SUCCESS",
        "additional_info": {}
    },
    "RunKey(config_id=39, instance_id=None, seed=0, budget=0.0)": {
        "cost": -3864.989202691005,
        "time": 0.013665199279785156,
        "status": "SUCCESS",
        "additional_info": {}
    },
    "RunKey(config_id=40, instance_id=None, seed=0, budget=0.0)": {
        "cost": -3826.845007625985,
        "time": 0.014411687850952148,
        "status": "SUCCESS",
        "additional_info": {}
    },
    "RunKey(config_id=41, instance_id=None, seed=0, budget=0.0)": {
        "cost": -3880.8182487646195,
        "time": 0.014454364776611328,
        "status": "SUCCESS",
        "additional_info": {}
    },
    "RunKey(config_id=42, instance_id=None, seed=0, budget=0.0)": {
        "cost": -3752.0190955828853,
        "time": 0.02406787872314453,
        "status": "SUCCESS",
        "additional_info": {}
    },
    "RunKey(config_id=43, instance_id=None, seed=0, budget=0.0)": {
        "cost": -3876.0614413577696,
        "time": 0.014365911483764648,
        "status": "SUCCESS",
        "additional_info": {}
    },
    "RunKey(config_id=44, instance_id=None, seed=0, budget=0.0)": {
        "cost": -3783.3850054088016,
        "time": 0.013910055160522461,
        "status": "SUCCESS",
        "additional_info": {}
    },
    "RunKey(config_id=45, instance_id=None, seed=0, budget=0.0)": {
        "cost": -3879.871693252067,
        "time": 0.024227142333984375,
        "status": "SUCCESS",
        "additional_info": {}
    },
    "RunKey(config_id=46, instance_id=None, seed=0, budget=0.0)": {
        "cost": -3864.5084157861515,
        "time": 0.0247499942779541,
        "status": "SUCCESS",
        "additional_info": {}
    },
    "RunKey(config_id=47, instance_id=None, seed=0, budget=0.0)": {
        "cost": -3882.225384228029,
        "time": 0.024846553802490234,
        "status": "SUCCESS",
        "additional_info": {}
    },
    "RunKey(config_id=48, instance_id=None, seed=0, budget=0.0)": {
        "cost": -3885.25080748148,
        "time": 0.024477720260620117,
        "status": "SUCCESS",
        "additional_info": {}
    },
    "RunKey(config_id=49, instance_id=None, seed=0, budget=0.0)": {
        "cost": -3872.054095740909,
        "time": 0.013506889343261719,
        "status": "SUCCESS",
        "additional_info": {}
    },
    "RunKey(config_id=50, instance_id=None, seed=0, budget=0.0)": {
        "cost": -3730.6996965101384,
        "time": 0.013816118240356445,
        "status": "SUCCESS",
        "additional_info": {}
    },
    "RunKey(config_id=51, instance_id=None, seed=0, budget=0.0)": {
        "cost": -3873.0753689129383,
        "time": 0.02458953857421875,
        "status": "SUCCESS",
        "additional_info": {}
    },
    "RunKey(config_id=52, instance_id=None, seed=0, budget=0.0)": {
        "cost": -3886.8167818631973,
        "time": 0.013585329055786133,
        "status": "SUCCESS",
        "additional_info": {}
    },
    "RunKey(config_id=53, instance_id=None, seed=0, budget=0.0)": {
        "cost": -3775.6644620696034,
        "time": 0.01297140121459961,
        "status": "SUCCESS",
        "additional_info": {}
    },
    "RunKey(config_id=54, instance_id=None, seed=0, budget=0.0)": {
        "cost": -3884.2697666551744,
        "time": 0.013689756393432617,
        "status": "SUCCESS",
        "additional_info": {}
    },
    "RunKey(config_id=55, instance_id=None, seed=0, budget=0.0)": {
        "cost": -3787.3761356921145,
        "time": 0.013017416000366211,
        "status": "SUCCESS",
        "additional_info": {}
    },
    "RunKey(config_id=56, instance_id=None, seed=0, budget=0.0)": {
        "cost": -3884.775472905152,
        "time": 0.02509021759033203,
        "status": "SUCCESS",
        "additional_info": {}
    },
    "RunKey(config_id=57, instance_id=None, seed=0, budget=0.0)": {
        "cost": -3873.5384471846883,
        "time": 0.013978719711303711,
        "status": "SUCCESS",
        "additional_info": {}
    },
    "RunKey(config_id=58, instance_id=None, seed=0, budget=0.0)": {
        "cost": -3877.1773419132182,
        "time": 0.013476371765136719,
        "status": "SUCCESS",
        "additional_info": {}
    },
    "RunKey(config_id=59, instance_id=None, seed=0, budget=0.0)": {
        "cost": -3881.5160932026133,
        "time": 0.024979591369628906,
        "status": "SUCCESS",
        "additional_info": {}
    },
    "RunKey(config_id=60, instance_id=None, seed=0, budget=0.0)": {
        "cost": -3776.8062760022235,
        "time": 0.013454675674438477,
        "status": "SUCCESS",
        "additional_info": {}
    },
    "RunKey(config_id=61, instance_id=None, seed=0, budget=0.0)": {
        "cost": -3750.7245791728883,
        "time": 0.012959718704223633,
        "status": "SUCCESS",
        "additional_info": {}
    },
    "RunKey(config_id=62, instance_id=None, seed=0, budget=0.0)": {
        "cost": -3876.050534610755,
        "time": 0.014559507369995117,
        "status": "SUCCESS",
        "additional_info": {}
    },
    "RunKey(config_id=63, instance_id=None, seed=0, budget=0.0)": {
        "cost": -3885.3140033942623,
        "time": 0.014224529266357422,
        "status": "SUCCESS",
        "additional_info": {}
    },
    "RunKey(config_id=64, instance_id=None, seed=0, budget=0.0)": {
        "cost": -3886.185038282403,
        "time": 0.013703107833862305,
        "status": "SUCCESS",
        "additional_info": {}
    },
    "RunKey(config_id=65, instance_id=None, seed=0, budget=0.0)": {
        "cost": -3879.7393866901216,
        "time": 0.014101028442382812,
        "status": "SUCCESS",
        "additional_info": {}
    },
    "RunKey(config_id=66, instance_id=None, seed=0, budget=0.0)": {
        "cost": -3775.3216722949296,
        "time": 0.013972997665405273,
        "status": "SUCCESS",
        "additional_info": {}
    },
    "RunKey(config_id=67, instance_id=None, seed=0, budget=0.0)": {
        "cost": -3882.7183092917794,
        "time": 0.02488875389099121,
        "status": "SUCCESS",
        "additional_info": {}
    },
    "RunKey(config_id=68, instance_id=None, seed=0, budget=0.0)": {
        "cost": -3889.8189699279983,
        "time": 0.014218568801879883,
        "status": "SUCCESS",
        "additional_info": {}
    },
    "RunKey(config_id=69, instance_id=None, seed=0, budget=0.0)": {
        "cost": -3870.8942071211823,
        "time": 0.013006210327148438,
        "status": "SUCCESS",
        "additional_info": {}
    },
    "RunKey(config_id=70, instance_id=None, seed=0, budget=0.0)": {
        "cost": -3879.1206512046438,
        "time": 0.014616966247558594,
        "status": "SUCCESS",
        "additional_info": {}
    },
    "RunKey(config_id=71, instance_id=None, seed=0, budget=0.0)": {
        "cost": -3882.3673652245734,
        "time": 0.014455318450927734,
        "status": "SUCCESS",
        "additional_info": {}
    },
    "RunKey(config_id=72, instance_id=None, seed=0, budget=0.0)": {
        "cost": -3889.3685329160558,
        "time": 0.013621807098388672,
        "status": "SUCCESS",
        "additional_info": {}
    },
    "RunKey(config_id=73, instance_id=None, seed=0, budget=0.0)": {
        "cost": -3876.4873601531726,
        "time": 0.013516664505004883,
        "status": "SUCCESS",
        "additional_info": {}
    },
    "RunKey(config_id=74, instance_id=None, seed=0, budget=0.0)": {
        "cost": -3882.029134590264,
        "time": 0.014014244079589844,
        "status": "SUCCESS",
        "additional_info": {}
    },
    "RunKey(config_id=75, instance_id=None, seed=0, budget=0.0)": {
        "cost": -3784.9876232469614,
        "time": 0.01403951644897461,
        "status": "SUCCESS",
        "additional_info": {}
    },
    "RunKey(config_id=76, instance_id=None, seed=0, budget=0.0)": {
        "cost": -3887.9189363108303,
        "time": 0.014569282531738281,
        "status": "SUCCESS",
        "additional_info": {}
    },
    "RunKey(config_id=77, instance_id=None, seed=0, budget=0.0)": {
        "cost": -3882.685222090513,
        "time": 0.013730287551879883,
        "status": "SUCCESS",
        "additional_info": {}
    },
    "RunKey(config_id=78, instance_id=None, seed=0, budget=0.0)": {
        "cost": -3875.420392544278,
        "time": 0.014296770095825195,
        "status": "SUCCESS",
        "additional_info": {}
    },
    "RunKey(config_id=79, instance_id=None, seed=0, budget=0.0)": {
        "cost": -3884.689789474629,
        "time": 0.014480352401733398,
        "status": "SUCCESS",
        "additional_info": {}
    },
    "RunKey(config_id=80, instance_id=None, seed=0, budget=0.0)": {
        "cost": -3890.6401683338468,
        "time": 0.025310277938842773,
        "status": "SUCCESS",
        "additional_info": {}
    },
    "RunKey(config_id=81, instance_id=None, seed=0, budget=0.0)": {
        "cost": -3752.5337063377465,
        "time": 0.014183282852172852,
        "status": "SUCCESS",
        "additional_info": {}
    },
    "RunKey(config_id=82, instance_id=None, seed=0, budget=0.0)": {
        "cost": -3873.387270275337,
        "time": 0.014275550842285156,
        "status": "SUCCESS",
        "additional_info": {}
    },
    "RunKey(config_id=83, instance_id=None, seed=0, budget=0.0)": {
        "cost": -3882.5195435111827,
        "time": 0.015238523483276367,
        "status": "SUCCESS",
        "additional_info": {}
    },
    "RunKey(config_id=84, instance_id=None, seed=0, budget=0.0)": {
        "cost": -3881.649544499878,
        "time": 0.013567209243774414,
        "status": "SUCCESS",
        "additional_info": {}
    },
    "RunKey(config_id=85, instance_id=None, seed=0, budget=0.0)": {
        "cost": -3891.3719024222437,
        "time": 0.014110803604125977,
        "status": "SUCCESS",
        "additional_info": {}
    },
    "RunKey(config_id=86, instance_id=None, seed=0, budget=0.0)": {
        "cost": -3887.662806587949,
        "time": 0.01292276382446289,
        "status": "SUCCESS",
        "additional_info": {}
    },
    "RunKey(config_id=87, instance_id=None, seed=0, budget=0.0)": {
        "cost": -3877.0000676966197,
        "time": 0.024494409561157227,
        "status": "SUCCESS",
        "additional_info": {}
    },
    "RunKey(config_id=88, instance_id=None, seed=0, budget=0.0)": {
        "cost": -3808.9500585878304,
        "time": 0.013623952865600586,
        "status": "SUCCESS",
        "additional_info": {}
    },
    "RunKey(config_id=89, instance_id=None, seed=0, budget=0.0)": {
        "cost": -3796.686577319721,
        "time": 0.014292716979980469,
        "status": "SUCCESS",
        "additional_info": {}
    },
    "RunKey(config_id=90, instance_id=None, seed=0, budget=0.0)": {
        "cost": -3878.834576305669,
        "time": 0.025231122970581055,
        "status": "SUCCESS",
        "additional_info": {}
    },
    "RunKey(config_id=91, instance_id=None, seed=0, budget=0.0)": {
        "cost": -3882.1924170472785,
        "time": 0.013663053512573242,
        "status": "SUCCESS",
        "additional_info": {}
    },
    "RunKey(config_id=92, instance_id=None, seed=0, budget=0.0)": {
        "cost": -3876.7844112694215,
        "time": 0.01419210433959961,
        "status": "SUCCESS",
        "additional_info": {}
    },
    "RunKey(config_id=93, instance_id=None, seed=0, budget=0.0)": {
        "cost": -3885.148687292046,
        "time": 0.014337778091430664,
        "status": "SUCCESS",
        "additional_info": {}
    },
    "RunKey(config_id=94, instance_id=None, seed=0, budget=0.0)": {
        "cost": -3885.137957549015,
        "time": 0.013869285583496094,
        "status": "SUCCESS",
        "additional_info": {}
    },
    "RunKey(config_id=95, instance_id=None, seed=0, budget=0.0)": {
        "cost": -3874.1948547362153,
        "time": 0.025030851364135742,
        "status": "SUCCESS",
        "additional_info": {}
    },
    "RunKey(config_id=96, instance_id=None, seed=0, budget=0.0)": {
        "cost": -3891.227696529868,
        "time": 0.013391971588134766,
        "status": "SUCCESS",
        "additional_info": {}
    },
    "RunKey(config_id=97, instance_id=None, seed=0, budget=0.0)": {
        "cost": -3884.197231443893,
        "time": 0.013344764709472656,
        "status": "SUCCESS",
        "additional_info": {}
    },
    "RunKey(config_id=98, instance_id=None, seed=0, budget=0.0)": {
        "cost": -3885.683062246123,
        "time": 0.024695873260498047,
        "status": "SUCCESS",
        "additional_info": {}
    },
    "RunKey(config_id=99, instance_id=None, seed=0, budget=0.0)": {
        "cost": -3898.00674865778,
        "time": 0.02437448501586914,
        "status": "SUCCESS",
        "additional_info": {}
    },
    "RunKey(config_id=100, instance_id=None, seed=0, budget=0.0)": {
        "cost": -3888.752711243211,
        "time": 0.02471470832824707,
        "status": "SUCCESS",
        "additional_info": {}
    }
}