{"cpu_time": 0.0, "wallclock_time": 0.010657310485839844, "evaluations": 0, "cost": 2147483648.0, "incumbent": {"autovacuum_analyze_scale_factor": 9.022416733205318, "autovacuum_analyze_threshold": 1098782943, "autovacuum_max_workers": 67, "autovacuum_naptime": 1298967, "autovacuum_vacuum_cost_delay": 83, "autovacuum_vacuum_cost_limit": 8117, "autovacuum_vacuum_scale_factor": 84.30853514000773, "autovacuum_vacuum_threshold": 1939469733, "backend_flush_after": 25, "bgwriter_delay": 2921, "bgwriter_flush_after": 174, "bgwriter_lru_maxpages": 582, "bgwriter_lru_multiplier": 7, "checkpoint_completion_target": 0.3461359143257141, "checkpoint_flush_after": 250, "checkpoint_timeout": 2284, "commit_delay": 36231, "commit_siblings": 954, "cursor_tuple_fraction": 0.1377423545345664, "deadlock_timeout": 1408939122, "default_statistics_target": 4358, "effective_cache_size": 1394533168, "effective_io_concurrency": 454, "from_collapse_limit": 1798991148, "geqo_effort": 3, "geqo_generations": 159642294, "geqo_pool_size": 1264875639, "geqo_seed": 0.41606879886239767, "geqo_threshold": 173074473, "join_collapse_limit": 74037612, "maintenance_work_mem": 957667097, "max_connections": 1419, "max_wal_senders": 22, "shared_buffers": 217296, "temp_buffers": 70276608, "temp_file_limit": 118208495, "vacuum_cost_delay": 63, "vacuum_cost_limit": 3691, "vacuum_cost_page_dirty": 4598, "vacuum_cost_page_hit": 7434, "vacuum_cost_page_miss": 312, "wal_buffers": 9358, "wal_writer_delay": 9009, "work_mem": 1668439634}, "budget": 0, "origin": "Sobol"}
{"cpu_time": 0.013821840286254883, "wallclock_time": 0.03018355369567871, "evaluations": 1, "cost": -3310.4691, "incumbent": {"autovacuum_analyze_scale_factor": 9.022416733205318, "autovacuum_analyze_threshold": 1098782943, "autovacuum_max_workers": 67, "autovacuum_naptime": 1298967, "autovacuum_vacuum_cost_delay": 83, "autovacuum_vacuum_cost_limit": 8117, "autovacuum_vacuum_scale_factor": 84.30853514000773, "autovacuum_vacuum_threshold": 1939469733, "backend_flush_after": 25, "bgwriter_delay": 2921, "bgwriter_flush_after": 174, "bgwriter_lru_maxpages": 582, "bgwriter_lru_multiplier": 7, "checkpoint_completion_target": 0.3461359143257141, "checkpoint_flush_after": 250, "checkpoint_timeout": 2284, "commit_delay": 36231, "commit_siblings": 954, "cursor_tuple_fraction": 0.1377423545345664, "deadlock_timeout": 1408939122, "default_statistics_target": 4358, "effective_cache_size": 1394533168, "effective_io_concurrency": 454, "from_collapse_limit": 1798991148, "geqo_effort": 3, "geqo_generations": 159642294, "geqo_pool_size": 1264875639, "geqo_seed": 0.41606879886239767, "geqo_threshold": 173074473, "join_collapse_limit": 74037612, "maintenance_work_mem": 957667097, "max_connections": 1419, "max_wal_senders": 22, "shared_buffers": 217296, "temp_buffers": 70276608, "temp_file_limit": 118208495, "vacuum_cost_delay": 63, "vacuum_cost_limit": 3691, "vacuum_cost_page_dirty": 4598, "vacuum_cost_page_hit": 7434, "vacuum_cost_page_miss": 312, "wal_buffers": 9358, "wal_writer_delay": 9009, "work_mem": 1668439634}, "budget": 0, "origin": "Sobol"}
{"cpu_time": 0.052106618881225586, "wallclock_time": 0.11040139198303223, "evaluations": 4, "cost": -3327.6585, "incumbent": {"autovacuum_analyze_scale_factor": 26.481935661286116, "autovacuum_analyze_threshold": 721596254, "autovacuum_max_workers": 190, "autovacuum_naptime": 1062135, "autovacuum_vacuum_cost_delay": 67, "autovacuum_vacuum_cost_limit": 5079, "autovacuum_vacuum_scale_factor": 1.2826400808990002, "autovacuum_vacuum_threshold": 1241364491, "backend_flush_after": 76, "bgwriter_delay": 477, "bgwriter_flush_after": 204, "bgwriter_lru_maxpages": 980, "bgwriter_lru_multiplier": 0, "checkpoint_completion_target": 0.7091427892446518, "checkpoint_flush_after": 141, "checkpoint_timeout": 41, "commit_delay": 6757, "commit_siblings": 195, "cursor_tuple_fraction": 0.46846663393080235, "deadlock_timeout": 341141914, "default_statistics_target": 8863, "effective_cache_size": 1715922758, "effective_io_concurrency": 572, "from_collapse_limit": 609895714, "geqo_effort": 6, "geqo_generations": 550156632, "geqo_pool_size": 891369298, "geqo_seed": 0.020743686705827713, "geqo_threshold": 1646830390, "join_collapse_limit": 874423020, "maintenance_work_mem": 1167999267, "max_connections": 1786, "max_wal_senders": 39, "shared_buffers": 1247105, "temp_buffers": 470443576, "temp_file_limit": 1005496917, "vacuum_cost_delay": 28, "vacuum_cost_limit": 8183, "vacuum_cost_page_dirty": 9458, "vacuum_cost_page_hit": 3934, "vacuum_cost_page_miss": 6476, "wal_buffers": 35589, "wal_writer_delay": 3725, "work_mem": 818438137}, "budget": 0, "origin": "Sobol"}
{"cpu_time": 0.1048574447631836, "wallclock_time": 0.20914745330810547, "evaluations": 8, "cost": -3338.6586, "incumbent": {"autovacuum_analyze_scale_factor": 68.1232750415802, "autovacuum_analyze_threshold": 1464507551, "autovacuum_max_workers": 167, "autovacuum_naptime": 260835, "autovacuum_vacuum_cost_delay": 29, "autovacuum_vacuum_cost_limit": 4223, "autovacuum_vacuum_scale_factor": 92.15154927223921, "autovacuum_vacuum_threshold": 1864409019, "backend_flush_after": 49, "bgwriter_delay": 1800, "bgwriter_flush_after": 153, "bgwriter_lru_maxpages": 104, "bgwriter_lru_multiplier": 6, "checkpoint_completion_target": 0.5672597279772162, "checkpoint_flush_after": 69, "checkpoint_timeout": 1531, "commit_delay": 99241, "commit_siblings": 341, "cursor_tuple_fraction": 0.006115379743278027, "deadlock_timeout": 1984482532, "default_statistics_target": 1414, "effective_cache_size": 250592792, "effective_io_concurrency": 351, "from_collapse_limit": 467357266, "geqo_effort": 10, "geqo_generations": 395675276, "geqo_pool_size": 1522604345, "geqo_seed": 0.15250328183174133, "geqo_threshold": 570257513, "join_collapse_limit": 1409068376, "maintenance_work_mem": 629937567, "max_connections": 608, "max_wal_senders": 35, "shared_buffers": 533398, "temp_buffers": 337236825, "temp_file_limit": 613530673, "vacuum_cost_delay": 40, "vacuum_cost_limit": 7487, "vacuum_cost_page_dirty": 3488, "vacuum_cost_page_hit": 963, "vacuum_cost_page_miss": 9247, "wal_buffers": 51689, "wal_writer_delay": 5403, "work_mem": 260375776}, "budget": 0, "origin": "Sobol"}
{"cpu_time": 0.2879600524902344, "wallclock_time": 0.4672572612762451, "evaluations": 22, "cost": -3364.6651, "incumbent": {"autovacuum_analyze_scale_factor": 38.14081698656082, "autovacuum_analyze_threshold": 1249090249, "autovacuum_max_workers": 177, "autovacuum_naptime": 1650355, "autovacuum_vacuum_cost_delay": 88, "autovacuum_vacuum_cost_limit": 3371, "autovacuum_vacuum_scale_factor": 18.92035761848092, "autovacuum_vacuum_threshold": 1693534407, "backend_flush_after": 256, "bgwriter_delay": 9864, "bgwriter_flush_after": 16, "bgwriter_lru_maxpages": 594, "bgwriter_lru_multiplier": 0, "checkpoint_completion_target": 0.32118713948875666, "checkpoint_flush_after": 194, "checkpoint_timeout": 641, "commit_delay": 94224, "commit_siblings": 521, "cursor_tuple_fraction": 0.06039774790406227, "deadlock_timeout": 1279054654, "default_statistics_target": 5205, "effective_cache_size": 390597560, "effective_io_concurrency": 661, "from_collapse_limit": 1540209128, "geqo_effort": 4, "geqo_generations": 1360415375, "geqo_pool_size": 1876379281, "geqo_seed": 0.2151053510606289, "geqo_threshold": 79299743, "join_collapse_limit": 560154010, "maintenance_work_mem": 1020556511, "max_connections": 420, "max_wal_senders": 50, "shared_buffers": 13639, "temp_buffers": 604703044, "temp_file_limit": 907131373, "vacuum_cost_delay": 43, "vacuum_cost_limit": 9811, "vacuum_cost_page_dirty": 1150, "vacuum_cost_page_hit": 7186, "vacuum_cost_page_miss": 7525, "wal_buffers": 67834, "wal_writer_delay": 2691, "work_mem": 1523757836}, "budget": 0, "origin": "Sobol"}
{"cpu_time": 0.37751269340515137, "wallclock_time": 9.807734489440918, "evaluations": 28, "cost": -3375.0595, "incumbent": {"autovacuum_analyze_scale_factor": 38.14081698656082, "autovacuum_analyze_threshold": 1249090249, "autovacuum_max_workers": 177, "autovacuum_naptime": 1650355, "autovacuum_vacuum_cost_delay": 88, "autovacuum_vacuum_cost_limit": 3802, "autovacuum_vacuum_scale_factor": 18.92035761848092, "autovacuum_vacuum_threshold": 1820939647, "backend_flush_after": 256, "bgwriter_delay": 9864, "bgwriter_flush_after": 16, "bgwriter_lru_maxpages": 539, "bgwriter_lru_multiplier": 0, "checkpoint_completion_target": 0.22021538434315419, "checkpoint_flush_after": 194, "checkpoint_timeout": 641, "commit_delay": 94224, "commit_siblings": 521, "cursor_tuple_fraction": 0.06039774790406227, "deadlock_timeout": 1279054654, "default_statistics_target": 5205, "effective_cache_size": 390597560, "effective_io_concurrency": 661, "from_collapse_limit": 1540209128, "geqo_effort": 7, "geqo_generations": 1360415375, "geqo_pool_size": 1876379281, "geqo_seed": 0.2151053510606289, "geqo_threshold": 79299743, "join_collapse_limit": 560154010, "maintenance_work_mem": 1020556511, "max_connections": 420, "max_wal_senders": 50, "shared_buffers": 25188, "temp_buffers": 604703044, "temp_file_limit": 865956863, "vacuum_cost_delay": 43, "vacuum_cost_limit": 9223, "vacuum_cost_page_dirty": 1150, "vacuum_cost_page_hit": 7186, "vacuum_cost_page_miss": 7525, "wal_buffers": 67834, "wal_writer_delay": 2691, "work_mem": 1636507535}, "budget": 0, "origin": "Local Search"}
{"cpu_time": 0.786123514175415, "wallclock_time": 86.27124166488647, "evaluations": 54, "cost": -3376.3573, "incumbent": {"autovacuum_analyze_scale_factor": 28.642095312555156, "autovacuum_analyze_threshold": 1339835391, "autovacuum_max_workers": 194, "autovacuum_naptime": 1650355, "autovacuum_vacuum_cost_delay": 90, "autovacuum_vacuum_cost_limit": 3466, "autovacuum_vacuum_scale_factor": 18.92035761848092, "autovacuum_vacuum_threshold": 1820939647, "backend_flush_after": 256, "bgwriter_delay": 9864, "bgwriter_flush_after": 11, "bgwriter_lru_maxpages": 539, "bgwriter_lru_multiplier": 0, "checkpoint_completion_target": 0.22021538434315419, "checkpoint_flush_after": 194, "checkpoint_timeout": 641, "commit_delay": 94224, "commit_siblings": 521, "cursor_tuple_fraction": 0.08669474370919922, "deadlock_timeout": 1289506816, "default_statistics_target": 5047, "effective_cache_size": 442520576, "effective_io_concurrency": 672, "from_collapse_limit": 1540209128, "geqo_effort": 7, "geqo_generations": 1153316095, "geqo_pool_size": 1876379281, "geqo_seed": 0.2151053510606289, "geqo_threshold": 116942009, "join_collapse_limit": 392739488, "maintenance_work_mem": 1092936182, "max_connections": 420, "max_wal_senders": 40, "shared_buffers": 29814, "temp_buffers": 604703044, "temp_file_limit": 865956863, "vacuum_cost_delay": 49, "vacuum_cost_limit": 9223, "vacuum_cost_page_dirty": 609, "vacuum_cost_page_hit": 7186, "vacuum_cost_page_miss": 7250, "wal_buffers": 65081, "wal_writer_delay": 2691, "work_mem": 1636507535}, "budget": 0, "origin": "Local Search"}
{"cpu_time": 1.0701172351837158, "wallclock_time": 157.04093170166016, "evaluations": 72, "cost": -3376.4282, "incumbent": {"autovacuum_analyze_scale_factor": 38.14081698656082, "autovacuum_analyze_threshold": 1348208639, "autovacuum_max_workers": 159, "autovacuum_naptime": 1638126, "autovacuum_vacuum_cost_delay": 88, "autovacuum_vacuum_cost_limit": 3461, "autovacuum_vacuum_scale_factor": 18.92035761848092, "autovacuum_vacuum_threshold": 1820939647, "backend_flush_after": 256, "bgwriter_delay": 9864, "bgwriter_flush_after": 16, "bgwriter_lru_maxpages": 539, "bgwriter_lru_multiplier": 0, "checkpoint_completion_target": 0.22021538434315419, "checkpoint_flush_after": 194, "checkpoint_timeout": 641, "commit_delay": 94224, "commit_siblings": 555, "cursor_tuple_fraction": 0.06039774790406227, "deadlock_timeout": 1433757696, "default_statistics_target": 4959, "effective_cache_size": 390597560, "effective_io_concurrency": 661, "from_collapse_limit": 1404025728, "geqo_effort": 7, "geqo_generations": 1026453184, "geqo_pool_size": 1815959679, "geqo_seed": 0.2151053510606289, "geqo_threshold": 79299743, "join_collapse_limit": 352589856, "maintenance_work_mem": 934341314, "max_connections": 420, "max_wal_senders": 2, "shared_buffers": 25188, "temp_buffers": 604703044, "temp_file_limit": 865956863, "vacuum_cost_delay": 53, "vacuum_cost_limit": 9035, "vacuum_cost_page_dirty": 1150, "vacuum_cost_page_hit": 7186, "vacuum_cost_page_miss": 7965, "wal_buffers": 66516, "wal_writer_delay": 2917, "work_mem": 1636507535}, "budget": 0, "origin": "Local Search"}
{"cpu_time": 1.0985260009765625, "wallclock_time": 162.57842707633972, "evaluations": 74, "cost": -3377.5235, "incumbent": {"autovacuum_analyze_scale_factor": 39.92718581212921, "autovacuum_analyze_threshold": 1284645375, "autovacuum_max_workers": 199, "autovacuum_naptime": 1650355, "autovacuum_vacuum_cost_delay": 90, "autovacuum_vacuum_cost_limit": 3446, "autovacuum_vacuum_scale_factor": 18.92035761848092, "autovacuum_vacuum_threshold": 1820939647, "backend_flush_after": 256, "bgwriter_delay": 9864, "bgwriter_flush_after": 11, "bgwriter_lru_maxpages": 539, "bgwriter_lru_multiplier": 0, "checkpoint_completion_target": 0.22021538434315419, "checkpoint_flush_after": 194, "checkpoint_timeout": 641, "commit_delay": 94224, "commit_siblings": 517, "cursor_tuple_fraction": 0.08669474370919922, "deadlock_timeout": 1289506816, "default_statistics_target": 5047, "effective_cache_size": 357959616, "effective_io_concurrency": 672, "from_collapse_limit": 1495682944, "geqo_effort": 10, "geqo_generations": 1153316095, "geqo_pool_size": 1876379281, "geqo_seed": 0.24607244105658357, "geqo_threshold": 190825169, "join_collapse_limit": 392739488, "maintenance_work_mem": 948108027, "max_connections": 420, "max_wal_senders": 44, "shared_buffers": 29814, "temp_buffers": 604703044, "temp_file_limit": 865956863, "vacuum_cost_delay": 47, "vacuum_cost_limit": 9223, "vacuum_cost_page_dirty": 609, "vacuum_cost_page_hit": 7186, "vacuum_cost_page_miss": 7692, "wal_buffers": 65081, "wal_writer_delay": 3156, "work_mem": 1636507535}, "budget": 0, "origin": "Local Search"}
{"cpu_time": 1.2395141124725342, "wallclock_time": 182.81110215187073, "evaluations": 81, "cost": -3379.6816, "incumbent": {"autovacuum_analyze_scale_factor": 40.20251215331312, "autovacuum_analyze_threshold": 1327600767, "autovacuum_max_workers": 192, "autovacuum_naptime": 1476112, "autovacuum_vacuum_cost_delay": 90, "autovacuum_vacuum_cost_limit": 2576, "autovacuum_vacuum_scale_factor": 18.92035761848092, "autovacuum_vacuum_threshold": 1820939647, "backend_flush_after": 256, "bgwriter_delay": 9864, "bgwriter_flush_after": 10, "bgwriter_lru_maxpages": 539, "bgwriter_lru_multiplier": 0, "checkpoint_completion_target": 0.22021538434315419, "checkpoint_flush_after": 194, "checkpoint_timeout": 636, "commit_delay": 94224, "commit_siblings": 555, "cursor_tuple_fraction": 0.06039774790406227, "deadlock_timeout": 1302147200, "default_statistics_target": 5203, "effective_cache_size": 344644064, "effective_io_concurrency": 661, "from_collapse_limit": 1540209128, "geqo_effort": 10, "geqo_generations": 1391530495, "geqo_pool_size": 1876379281, "geqo_seed": 0.24158748766959356, "geqo_threshold": 60184477, "join_collapse_limit": 560154010, "maintenance_work_mem": 931674051, "max_connections": 298, "max_wal_senders": 47, "shared_buffers": 49335, "temp_buffers": 604703044, "temp_file_limit": 865956863, "vacuum_cost_delay": 56, "vacuum_cost_limit": 9223, "vacuum_cost_page_dirty": 1080, "vacuum_cost_page_hit": 7790, "vacuum_cost_page_miss": 8046, "wal_buffers": 67834, "wal_writer_delay": 2691, "work_mem": 1681666317}, "budget": 0, "origin": "Local Search"}
{"cpu_time": 1.400585651397705, "wallclock_time": 227.78540349006653, "evaluations": 92, "cost": -3388.6828, "incumbent": {"autovacuum_analyze_scale_factor": 26.10754271991346, "autovacuum_analyze_threshold": 1406028671, "autovacuum_max_workers": 171, "autovacuum_naptime": 2010794, "autovacuum_vacuum_cost_delay": 90, "autovacuum_vacuum_cost_limit": 2576, "autovacuum_vacuum_scale_factor": 18.92035761848092, "autovacuum_vacuum_threshold": 1820939647, "backend_flush_after": 256, "bgwriter_delay": 9864, "bgwriter_flush_after": 2, "bgwriter_lru_maxpages": 542, "bgwriter_lru_multiplier": 0, "checkpoint_completion_target": 0.22021538434315419, "checkpoint_flush_after": 194, "checkpoint_timeout": 636, "commit_delay": 95330, "commit_siblings": 555, "cursor_tuple_fraction": 0.06039774790406227, "deadlock_timeout": 1327521280, "default_statistics_target": 5387, "effective_cache_size": 344644064, "effective_io_concurrency": 661, "from_collapse_limit": 1490264448, "geqo_effort": 10, "geqo_generations": 1391530495, "geqo_pool_size": 1876379281, "geqo_seed": 0.19797774123714032, "geqo_threshold": 247938145, "join_collapse_limit": 729384064, "maintenance_work_mem": 1005938144, "max_connections": 211, "max_wal_senders": 47, "shared_buffers": 49335, "temp_buffers": 671732005, "temp_file_limit": 865956863, "vacuum_cost_delay": 56, "vacuum_cost_limit": 9223, "vacuum_cost_page_dirty": 1281, "vacuum_cost_page_hit": 7790, "vacuum_cost_page_miss": 7107, "wal_buffers": 63343, "wal_writer_delay": 2691, "work_mem": 1589453968}, "budget": 0, "origin": "Local Search"}
